{"nodes": [{"id": "about", "label": "About", "file_type": "code", "source_file": "src/features/about/components/about.tsx", "source_location": "L40", "source_url": null, "captured_at": null, "author": null, "contributor": null}], "edges": [{"source": "about", "target": "get_age_from_dob", "relation": "calls", "confidence": "EXTRACTED", "confidence_score": 1.0, "source_file": "src/features/about/components/about.tsx", "source_location": "L9", "weight": 1.0}, {"source": "about", "target": "cloudinary_image", "relation": "calls", "confidence": "EXTRACTED", "confidence_score": 1.0, "source_file": "src/features/about/components/about.tsx", "source_location": "L45", "weight": 1.0}, {"source": "about", "target": "basic_markdown", "relation": "calls", "confidence": "EXTRACTED", "confidence_score": 1.0, "source_file": "src/features/about/components/about.tsx", "source_location": "L48", "weight": 1.0}, {"source": "about", "target": "fade_staggered_animation", "relation": "calls", "confidence": "EXTRACTED", "confidence_score": 1.0, "source_file": "src/features/about/components/about.tsx", "source_location": "L42", "weight": 1.0}], "hyperedges": []}